idleTime/__init__.py
idleTime/idle.py
idleTime-0.5.0.2.dist-info/LICENSE
idleTime-0.5.0.2.dist-info/METADATA
idleTime-0.5.0.2.dist-info/WHEEL
idleTime-0.5.0.2.dist-info/top_level.txt
idleTime-0.5.0.2.dist-info/RECORD
