Metadata-Version: 2.1
Name: idleTime
Version: 0.5.0.2
Summary: Usage of module gives the idle time of the computer. Note: Linux requires xprintidle. Use "sudo apt install xprintidle" for the module to work.
Home-page: https://github.com/TheSinOfSloth/idle_time
Author: S Ashwin
Author-email: ashwins1211@gmail.com
License: MIT
Download-URL: https://github.com/TheSinOfSloth/idle_time/archive/0.5.0.2.tar.gz
Keywords: idle,time,xprintidle
Platform: UNKNOWN
Classifier: Development Status :: 3 - Alpha
Classifier: Intended Audience :: Developers
Classifier: Topic :: Software Development :: Build Tools
Classifier: License :: OSI Approved :: MIT License
Classifier: Programming Language :: Python :: 3
Classifier: Programming Language :: Python :: 3.4
Classifier: Programming Language :: Python :: 3.5
Classifier: Programming Language :: Python :: 3.6
